hazelbean/__init__.py
hazelbean/arrayframe.py
hazelbean/arrayframe_functions.py
hazelbean/arrayframe_numpy_functions.py
hazelbean/cat_ears.py
hazelbean/cloud_utils.py
hazelbean/cog.py
hazelbean/config.py
hazelbean/conventions.py
hazelbean/core.py
hazelbean/data_structures.py
hazelbean/file_io.py
hazelbean/geoprocessing.py
hazelbean/geoprocessing_extension.py
hazelbean/globals.py
hazelbean/integration_testing_utils.py
hazelbean/json_helper.py
hazelbean/netcdf.py
hazelbean/os_utils.py
hazelbean/parallel.py
hazelbean/pog.py
hazelbean/project_flow.py
hazelbean/pyramids.py
hazelbean/raster_vector_interface.py
hazelbean/slow_config.py
hazelbean/spatial_projection.py
hazelbean/spatial_utils.py
hazelbean/stats.py
hazelbean/utils.py
hazelbean/vector.py
hazelbean/visualization.py
hazelbean/watershed_processing.py
hazelbean/bin/cogger/LICENSE
hazelbean/bin/cogger/README.md
hazelbean/bin/cogger/cogger.exe
hazelbean/calculation_core/__init__.py
hazelbean/calculation_core/aspect_ratio_array_functions.cp311-win_amd64.pyd
hazelbean/calculation_core/aspect_ratio_array_functions.pyx
hazelbean/calculation_core/compile_cython_functions.py
hazelbean/calculation_core/cython_functions.cp311-win_amd64.pyd
hazelbean/calculation_core/cython_functions.pyx
hazelbean/ui/__init__.py
hazelbean/ui/auto_ui.py
hazelbean/ui/auto_ui_tg.py
hazelbean/ui/cli.py
hazelbean/ui/datastack.py
hazelbean/ui/execution.py
hazelbean/ui/inputs.py
hazelbean/ui/launcher.py
hazelbean/ui/model.py
hazelbean/ui/usage.py
hazelbean/ui/usage_logger.py
hazelbean/ui/utils.py
hazelbean/ui/validation.py
hazelbean/ui/examples/carbon.py
hazelbean/ui/examples/cbc.py
hazelbean/ui/examples/crop_production.py
hazelbean/ui/examples/cv.py
hazelbean/ui/examples/finfish.py
hazelbean/ui/examples/fisheries.py
hazelbean/ui/examples/forest_carbon.py
hazelbean/ui/examples/globio.py
hazelbean/ui/examples/habitat_quality.py
hazelbean/ui/examples/hra.py
hazelbean/ui/examples/hydropower.py
hazelbean/ui/examples/ndr.py
hazelbean-1.8.0.dist-info/licenses/LICENSE
hazelbean-1.8.0.dist-info/METADATA
hazelbean-1.8.0.dist-info/WHEEL
hazelbean-1.8.0.dist-info/top_level.txt
hazelbean-1.8.0.dist-info/RECORD
