Metadata-Version: 2.4
Name: hazelbean
Version: 1.8.0
Summary: Collection of geospatial algorithms, parallel computation utilities and project management tools.
Author: Justin Andrew Johnson
Maintainer: Justin Andrew Johnson
License: https://creativecommons.org/licenses/by-nc-sa/4.0/legalcode
Project-URL: homepage, https://github.com/jandrewjohnson/hazelbean_dev
Keywords: gis,geospatial,economics,land use
Classifier: Development Status :: 5 - Production/Stable
Classifier: Intended Audience :: Science/Research
Classifier: Programming Language :: Cython
Classifier: Programming Language :: Python :: 3
Requires-Python: >=3.10
License-File: LICENSE
Requires-Dist: Pyro4
Requires-Dist: aenum
Requires-Dist: anytree
Requires-Dist: cython
Requires-Dist: dask
Requires-Dist: descartes
Requires-Dist: gdal
Requires-Dist: geopandas
Requires-Dist: google-api-python-client
Requires-Dist: google-auth
Requires-Dist: google-auth-oauthlib
Requires-Dist: google-cloud-datastore
Requires-Dist: google-cloud-storage
Requires-Dist: markdown
Requires-Dist: matplotlib
Requires-Dist: natcap.invest
Requires-Dist: netcdf4
Requires-Dist: numpy
Requires-Dist: openpyxl
Requires-Dist: pandas
Requires-Dist: pillow
Requires-Dist: pygeoprocessing
Requires-Dist: pytest
Requires-Dist: pytest-cov
Requires-Dist: pytest-benchmark
Requires-Dist: python-pptx
Requires-Dist: pyyaml
Requires-Dist: qtawesome
Requires-Dist: qtpy
Requires-Dist: requests
Requires-Dist: rioxarray
Requires-Dist: scikit-learn
Requires-Dist: scipy
Requires-Dist: seaborn
Requires-Dist: setuptools>=70.0.0
Requires-Dist: setuptools_scm
Requires-Dist: shapely
Requires-Dist: sip
Requires-Dist: six
Requires-Dist: statsmodels
Requires-Dist: taskgraph
Requires-Dist: tqdm
Requires-Dist: xarray
Requires-Dist: xlrd
Dynamic: license-file
Dynamic: requires-dist
